securelogging/__init__.py
securelogging-1.0.1.dist-info/METADATA
securelogging-1.0.1.dist-info/WHEEL
securelogging-1.0.1.dist-info/licenses/AUTHORS.rst
securelogging-1.0.1.dist-info/licenses/LICENSE.txt
securelogging-1.0.1.dist-info/RECORD
