Metadata-Version: 2.4
Name: securelogging
Version: 1.0.1
Summary: Remove secrets from logging
Project-URL: Repository, https://github.com/Expl0dingBanana/securelogging
Project-URL: Changelog, https://github.com/Expl0dingBanana/securelogging/CHANGELOG.md
Author-email: Chris Dohmen <chris.dohmen11@gmail.com>
Maintainer-email: Chris Dohmen <chris.dohmen11@gmail.com>
License: The MIT License (MIT)
License-File: AUTHORS.rst
License-File: LICENSE.txt
Keywords: logging,logging redactor,secrets
Classifier: Development Status :: 4 - Beta
Classifier: Programming Language :: Python
Classifier: Programming Language :: Python :: 3.8
Classifier: Programming Language :: Python :: 3.9
Classifier: Programming Language :: Python :: 3.10
Classifier: Programming Language :: Python :: 3.11
Classifier: Programming Language :: Python :: 3.12
Classifier: Programming Language :: Python :: 3.13
Requires-Python: >=3.8
Provides-Extra: testing
Requires-Dist: pytest; extra == 'testing'
Requires-Dist: pytest-cov; extra == 'testing'
Requires-Dist: tox; extra == 'testing'
